{
  "aliens": ["cnt-152"],
  "cockroaches": ["my-bs-27", "my-bs-47", "my-bs-54", "my-sl-34", "cnt-30"],
  "rats": ["my-bs-27", "my-hs-03", "my-hs-20", "my-hs-37", "my-pr-32", "my-sl-06", "st-bs-74", "st-bs-60"],
  "scorpions": ["my-bs-42"],
  "snakes": [
    "cnt-48",
    "cnt-94",
    "dc-b1-28",
    "dc-b1-34",
    "dc-b1-59",
    "dx-an-50",
    "dx-an-71",
    "dx-dd-10",
    "dx-dd-53",
    "dx-dd-75",
    "dd-hm-22",
    "dd-hm-67",
    "dx-mm-16",
    "dx-mm-34",
    "dx-mr-20",
    "dx-mr-21",
    "dx-mr-72",
    "dx-od-47",
    "dx-od-76",
    "dx-or-10",
    "dx-or-17",
    "dx-or-18",
    "dx-or-28",
    "dx-rv-42",
    "mu-aw-09",
    "mu-aw-35",
    "mu-aw-38",
    "mu-aw-73",
    "mu-aw-80",
    "my-bs-01",
    "my-bs-35",
    "my-bs-51",
    "my-bs-60",
    "my-hs-08",
    "my-hs-17",
    "my-hs-24",
    "my-pr-14",
    "my-pr-24",
    "my-pr-50",
    "my-pr-55",
    "st-bs-02",
    "st-bs-24",
    "st-bs-63"
  ],
  "spiders": ["dx-dd-62", "dd-hm-22", "dx-mr-35", "my-bs-10", "my-hs-34", "my-sl-23"]
}
